pydens/__init__.py
pydens/model_torch.py
pydens/batchflow/__init__.py
pydens/batchflow/check_release_version.py
pydens/batchflow/setup.py
pydens/batchflow/batchflow/__init__.py
pydens/batchflow/batchflow/_const.py
pydens/batchflow/batchflow/_fake.py
pydens/batchflow/batchflow/base.py
pydens/batchflow/batchflow/batch.py
pydens/batchflow/batchflow/batch_image.py
pydens/batchflow/batchflow/components.py
pydens/batchflow/batchflow/config.py
pydens/batchflow/batchflow/dataset.py
pydens/batchflow/batchflow/decorators.py
pydens/batchflow/batchflow/dsindex.py
pydens/batchflow/batchflow/exceptions.py
pydens/batchflow/batchflow/model_dir.py
pydens/batchflow/batchflow/monitor.py
pydens/batchflow/batchflow/named_expr.py
pydens/batchflow/batchflow/notifier.py
pydens/batchflow/batchflow/once_pipeline.py
pydens/batchflow/batchflow/pipeline.py
pydens/batchflow/batchflow/pipeline_executor.py
pydens/batchflow/batchflow/profiler.py
pydens/batchflow/batchflow/sampler.py
pydens/batchflow/batchflow/utils.py
pydens/batchflow/batchflow/utils_notebook.py
pydens/batchflow/batchflow/utils_random.py
pydens/batchflow/batchflow/utils_telegram.py
pydens/batchflow/batchflow/variables.py
pydens/batchflow/batchflow/models/__init__.py
pydens/batchflow/batchflow/models/base.py
pydens/batchflow/batchflow/models/sklearn.py
pydens/batchflow/batchflow/models/utils.py
pydens/batchflow/batchflow/models/metrics/__init__.py
pydens/batchflow/batchflow/models/metrics/base.py
pydens/batchflow/batchflow/models/metrics/classify.py
pydens/batchflow/batchflow/models/metrics/loss.py
pydens/batchflow/batchflow/models/metrics/regression.py
pydens/batchflow/batchflow/models/metrics/segment.py
pydens/batchflow/batchflow/models/metrics/utils.py
pydens/batchflow/batchflow/models/torch/__init__.py
pydens/batchflow/batchflow/models/torch/base.py
pydens/batchflow/batchflow/models/torch/blocks.py
pydens/batchflow/batchflow/models/torch/densenet.py
pydens/batchflow/batchflow/models/torch/efficientnet.py
pydens-1.0.2.dist-info/LICENSE
pydens-1.0.2.dist-info/METADATA
pydens-1.0.2.dist-info/WHEEL
pydens-1.0.2.dist-info/top_level.txt
pydens-1.0.2.dist-info/RECORD
