Metadata-Version: 2.1
Name: pydens
Version: 1.0.2
Summary: Framework for solving differential equations with deep learning
Home-page: https://github.com/analysiscenter/pydens.git
Author: Data Analysis Center
Author-email: akoriagin@nes.ru
License: Apache License 2.0
Platform: any
Classifier: Development Status :: 4 - Beta
Classifier: Intended Audience :: Developers
Classifier: Intended Audience :: Science/Research
Classifier: License :: OSI Approved :: Apache Software License
Classifier: Operating System :: OS Independent
Classifier: Programming Language :: Python
Classifier: Programming Language :: Python :: 3
Classifier: Programming Language :: Python :: 3.5
Classifier: Programming Language :: Python :: 3.6
Classifier: Programming Language :: Python :: 3.7
Classifier: Topic :: Scientific/Engineering
License-File: LICENSE
Requires-Dist: numpy (>=1.10)
Requires-Dist: dill (>=0.2.7)
Requires-Dist: tqdm (>=4.19.7)
Requires-Dist: scipy (>=0.19.1)
Requires-Dist: scikit-image (>=0.13.1)
Requires-Dist: numba (>=0.42)
